{
  "GUID": "2eb627",
  "Name": "Custom_Model",
  "Transform": {
    "posX": 27.4653664,
    "posY": 0.8124451,
    "posZ": -9.819787,
    "rotX": -2.358567e-7,
    "rotY": 359.9679,
    "rotZ": 2.11194489e-7,
    "scaleX": 1,
    "scaleY": 1,
    "scaleZ": 1
  },
  "Nickname": "Objective ",
  "Description": "",
  "GMNotes": "",
  "AltLookAngle": {
    "x": 0,
    "y": 0,
    "z": 0
  },
  "ColorDiffuse": {
    "r": 1,
    "g": 1,
    "b": 1
  },
  "LayoutGroupSortIndex": 0,
  "Value": 0,
  "Locked": false,
  "Grid": true,
  "Snap": true,
  "IgnoreFoW": false,
  "MeasureMovement": false,
  "DragSelectable": true,
  "Autoraise": true,
  "Sticky": true,
  "Tooltip": true,
  "GridProjection": false,
  "HideWhenFaceDown": false,
  "Hands": false,
  "CustomMesh": {
    "MeshURL": "https://steamusercontent-a.akamaihd.net/ugc/1012689151634465584/A6C540D6826E3F0C6A04C3BAEACD00219918F0A4/",
    "DiffuseURL": "https://steamusercontent-a.akamaihd.net/ugc/46823854549522549/184FCC5D0E38ACFF4E0D3286585224AA78F9307D/",
    "NormalURL": "",
    "ColliderURL": "https://steamusercontent-a.akamaihd.net/ugc/1012689151634465584/A6C540D6826E3F0C6A04C3BAEACD00219918F0A4/",
    "Convex": true,
    "MaterialIndex": 3,
    "TypeIndex": 1,
    "CustomShader": {
      "SpecularColor": {
        "r": 1,
        "g": 1,
        "b": 1
      },
      "SpecularIntensity": 0,
      "SpecularSharpness": 2,
      "FresnelStrength": 0
    },
    "CastShadows": true
  },
  "LuaScript": "radiuses = {0, 1.5, 2.5, 3.5, 6.5, 8.5, 12.5, 18.5, 24.5, 30.5}\r\nshowCircle = false\r\n\r\nfunction onScriptingButtonDown(index, playerColor)\r\n\tif Player[playerColor].getHoverObject() == self then\r\n\t\tprint(math.floor(radiuses[index]) .. '\" radius')\r\n\t\ttoggleCircle(radiuses[index])\r\n\tend\r\nend\r\n\r\nfunction toggleCircle(radius)\r\n\tshowCircle = not showCircle\r\n\tif showCircle then\r\n\t\tself.setVectorLines({\r\n\t\t\t{\r\n\t\t\t\tpoints    = getCircleVectorPoints(radius),\r\n\t\t\t\tcolor     = {0, 0.8, 0.4},\r\n\t\t\t\tthickness = 0.05,\r\n\t\t\t\trotation  = {0,0,0},\r\n\t\t\t}\r\n\t\t})\r\n\telse\r\n\t\tself.setVectorLines({})\r\n\tend\r\nend\r\n\r\nfunction getCircleVectorPoints(radius)\r\n\tlocal t = {}\r\n\tlocal step = 0.0981747704247\r\n\tlocal cos, sin = math.cos, math.sin\r\n\tlocal rdi = 0\r\n\tfor i = 0, 64 do\r\n\t\tt[i + 1] = { cos(rdi)*radius, 0.1, sin(rdi)*radius }\r\n\t\trdi = rdi + step\r\n\tend\r\n\treturn t\r\nend",
  "LuaScriptState": "",
  "XmlUI": ""
}